medrxiv_server.py
medrxiv_web_search.py
iflow_mcp_mcp_server_medrxiv-0.1.0.dist-info/METADATA
iflow_mcp_mcp_server_medrxiv-0.1.0.dist-info/WHEEL
iflow_mcp_mcp_server_medrxiv-0.1.0.dist-info/entry_points.txt
iflow_mcp_mcp_server_medrxiv-0.1.0.dist-info/top_level.txt
iflow_mcp_mcp_server_medrxiv-0.1.0.dist-info/RECORD
